handle_error/__init__.py
handle_error-0.0.7.dist-info/METADATA
handle_error-0.0.7.dist-info/WHEEL
handle_error-0.0.7.dist-info/top_level.txt
handle_error-0.0.7.dist-info/RECORD
