Metadata-Version: 2.1
Name: handle-error
Version: 0.0.7
Summary: handle error
Author: CrackCodeGenius
Author-email: artart56g@gmail.com
Keywords: python,handle_error,pip error
Classifier: Development Status :: 1 - Planning
Classifier: Intended Audience :: Developers
Classifier: Programming Language :: Python :: 3
Classifier: Operating System :: Unix
Classifier: Operating System :: MacOS :: MacOS X
Classifier: Operating System :: Microsoft :: Windows
